enforce_typing/__init__.py
enforce_typing/decorator.py
enforce_typing-1.0.0.post1.dist-info/LICENSE
enforce_typing-1.0.0.post1.dist-info/METADATA
enforce_typing-1.0.0.post1.dist-info/WHEEL
enforce_typing-1.0.0.post1.dist-info/top_level.txt
enforce_typing-1.0.0.post1.dist-info/RECORD
