Metadata-Version: 2.1
Name: enforce-typing
Version: 1.0.0.post1
Summary: An easy to use decorator to enforce static typing for function and dataclasses.
Home-page: https://github.com/matchawine/python-enforce-typing
Author: Joshua Logan
Author-email: joshua@matcha.wine
License: GPL
Keywords: decorators typing
Platform: UNKNOWN
Classifier: Development Status :: 5 - Production/Stable
Classifier: Environment :: Plugins
Classifier: Intended Audience :: Developers
Classifier: License :: OSI Approved :: GNU General Public License (GPL)
Classifier: Operating System :: OS Independent
Classifier: Natural Language :: English
Classifier: Programming Language :: Python :: 3.5
Classifier: Programming Language :: Python :: 3.6
Classifier: Programming Language :: Python :: 3.7
Classifier: Programming Language :: Python :: 3.8
Classifier: Topic :: Software Development :: Libraries :: Python Modules
Requires-Python: >=3.5
